{
  "last_updated": "2026-07-11T13:42:49.813433+00:00",
  "headlines": [
    {
      "title": "Candriam S.C.A. Has $62.85 Million Position in Bank of America Corporation $BAC",
      "url": "https://www.marketbeat.com/instant-alerts/filing-candriam-sca-has-6285-million-position-in-bank-of-america-corporation-bac-2026-07-11/",
      "source": "marketbeat.com",
      "published": "2026-07-11T13:20:46+00:00",
      "tickers": [
        "BAC",
        "C"
      ]
    },
    {
      "title": "Candriam S.C.A. Raises Stock Holdings in The Charles Schwab Corporation $SCHW",
      "url": "https://www.marketbeat.com/instant-alerts/filing-candriam-sca-raises-stock-holdings-in-the-charles-schwab-corporation-schw-2026-07-11/",
      "source": "marketbeat.com",
      "published": "2026-07-11T13:20:42+00:00",
      "tickers": [
        "C",
        "SCHW"
      ]
    },
    {
      "title": "Morgan Stanley $MS Shares Purchased by Candriam S.C.A.",
      "url": "https://www.marketbeat.com/instant-alerts/filing-morgan-stanley-ms-shares-purchased-by-candriam-sca-2026-07-11/",
      "source": "marketbeat.com",
      "published": "2026-07-11T13:20:41+00:00",
      "tickers": [
        "MS"
      ]
    },
    {
      "title": "U.S. Bancorp $USB Shares Bought by Conning Inc.",
      "url": "https://www.marketbeat.com/instant-alerts/filing-us-bancorp-usb-shares-bought-by-conning-inc-2026-07-11/",
      "source": "marketbeat.com",
      "published": "2026-07-11T13:13:04+00:00",
      "tickers": [
        "USB"
      ]
    },
    {
      "title": "The PNC Financial Services Group, Inc $PNC Shares Bought by Conning Inc.",
      "url": "https://www.marketbeat.com/instant-alerts/filing-the-pnc-financial-services-group-inc-pnc-shares-bought-by-conning-inc-2026-07-11/",
      "source": "marketbeat.com",
      "published": "2026-07-11T13:13:00+00:00",
      "tickers": [
        "C",
        "PNC"
      ]
    },
    {
      "title": "Conning Inc. Has $37.14 Million Stock Position in Morgan Stanley $MS",
      "url": "https://www.marketbeat.com/instant-alerts/filing-conning-inc-has-3714-million-stock-position-in-morgan-stanley-ms-2026-07-11/",
      "source": "marketbeat.com",
      "published": "2026-07-11T13:12:58+00:00",
      "tickers": [
        "MS"
      ]
    },
    {
      "title": "Dow Jones Futures: Watch Nvidia, Micron, Sandisk, Robinhood As Market Sets Up; Big Earnings Due",
      "url": "https://finance.yahoo.com/m/082a233e-c56a-3b99-a968-08ce2bfc43f7/dow-jones-futures%3A-watch.html?.tsrc=rss",
      "source": "yahoo.com",
      "published": "2026-07-11T12:49:37+00:00",
      "tickers": [
        "GS"
      ]
    },
    {
      "title": "State Street Corporation $STT Shares Bought by First Horizon Corp",
      "url": "https://www.marketbeat.com/instant-alerts/filing-state-street-corporation-stt-shares-bought-by-first-horizon-corp-2026-07-11/",
      "source": "marketbeat.com",
      "published": "2026-07-11T12:48:47+00:00",
      "tickers": [
        "STT"
      ]
    },
    {
      "title": "Beacon Harbor Wealth Advisors Inc. Invests $6.75 Million in Citigroup Inc. $C",
      "url": "https://www.marketbeat.com/instant-alerts/filing-beacon-harbor-wealth-advisors-inc-invests-675-million-in-citigroup-inc-c-2026-07-11/",
      "source": "marketbeat.com",
      "published": "2026-07-11T12:17:17+00:00",
      "tickers": [
        "C"
      ]
    },
    {
      "title": "5 Relatively Secure And Cheap Dividend Stocks, Yields Up To 8% (July 2026) | $WFC $NWG $KBCSY $ARCC $PGR",
      "url": "https://seekingalpha.com/article/4920377-5-relatively-secure-and-cheap-dividend-stocks-yields-up-to-8-percent-july-2026",
      "source": "seekingalpha.com",
      "published": "2026-07-11T12:15:00+00:00",
      "tickers": [
        "WFC",
        "C"
      ]
    },
    {
      "title": "AlpenGlobal Capital LLC Takes Position in The Goldman Sachs Group, Inc. $GS",
      "url": "https://www.marketbeat.com/instant-alerts/filing-alpenglobal-capital-llc-takes-position-in-the-goldman-sachs-group-inc-gs-2026-07-11/",
      "source": "marketbeat.com",
      "published": "2026-07-11T12:08:54+00:00",
      "tickers": [
        "GS"
      ]
    },
    {
      "title": "Palantir, Microsoft, Figma emerge as key AI beneficiaries ahead of Q2 software earnings: Citi",
      "url": "https://seekingalpha.com/news/4613033-palantir-microsoft-figma-emerge-as-key-ai-beneficiaries-ahead-of-q2-software-earnings-citi",
      "source": "seekingalpha.com",
      "published": "2026-07-11T12:00:49+00:00",
      "tickers": [
        "C"
      ]
    },
    {
      "title": "The World’s First Trillionaire and the Company He Won’t Let Go",
      "url": "https://www.bloomberg.com/news/newsletters/2026-07-11/the-world-s-first-trillionaire-and-the-company-he-won-t-let-go",
      "source": "bloomberg.com",
      "published": "2026-07-11T12:00:01+00:00",
      "tickers": [
        "JPM"
      ]
    },
    {
      "title": "Citigroup: Traders Are Getting Too Excited About Capital Markets Growth (Rating Downgrade) | $C",
      "url": "https://seekingalpha.com/article/4921300-citigroup-traders-are-getting-too-excited-about-capital-markets-growth",
      "source": "seekingalpha.com",
      "published": "2026-07-11T12:00:00+00:00",
      "tickers": [
        "C"
      ]
    },
    {
      "title": "How To Earn $500 A Month From Wells Fargo Stock Ahead Of Q2 Earnings",
      "url": "https://finance.yahoo.com/markets/stocks/articles/earn-500-month-wells-fargo-113121312.html?.tsrc=rss",
      "source": "yahoo.com",
      "published": "2026-07-11T11:31:21+00:00",
      "tickers": [
        "WFC",
        "C"
      ]
    },
    {
      "title": "Goldman Sachs Says Optical Networking Is AI’s Next Trillion-Dollar Opportunity. Lumentum May Be the Biggest Winner",
      "url": "https://247wallst.com/investing/2026/07/11/goldman-sachs-says-optical-networking-is-ais-next-trillion-dollar-opportunity-lumentum-may-be-the-biggest-winner/",
      "source": "247wallst.com",
      "published": "2026-07-11T11:30:48+00:00",
      "tickers": [
        "GS"
      ]
    },
    {
      "title": "‘The first time ever in my career’: Senior Citi executive on why the ultrawealthy want to diversify away from America",
      "url": "https://fortune.com/2026/07/11/why-are-ultrawealthy-americans-leaving-us-citigroup/",
      "source": "fortune.com",
      "published": "2026-07-11T11:30:28+00:00",
      "tickers": [
        "C"
      ]
    },
    {
      "title": "Morgan Stanley buys another 1,000 Bitcoin as holdings top 5,700 BTC",
      "url": "https://crypto.news/morgan-stanley-buys-1000-bitcoin-as-holdings-top-5700/",
      "source": "crypto.news",
      "published": "2026-07-11T10:52:54+00:00",
      "tickers": [
        "MS"
      ]
    },
    {
      "title": "U.S. Bancorp (USB) Launches Enhanced Payments, Is The Stock Fully Valued?",
      "url": "https://finance.yahoo.com/markets/stocks/articles/u-bancorp-usb-launches-enhanced-100953398.html?.tsrc=rss",
      "source": "yahoo.com",
      "published": "2026-07-11T10:09:53+00:00",
      "tickers": [
        "USB"
      ]
    },
    {
      "title": "Goldman Sachs warns the US will bear the brunt of a global AI-induced inflation surge",
      "url": "https://www.businessinsider.com/us-inflation-outlook-economy-ai-memory-software-prices-goldman-sachs-2026-7",
      "source": "businessinsider.com",
      "published": "2026-07-11T09:10:01+00:00",
      "tickers": [
        "GS"
      ]
    },
    {
      "title": "The K-Shaped Economy Revisited: The Hidden Divide Behind America's Resilient Consumer",
      "url": "https://thepeopleseconomist.substack.com/p/the-k-shaped-economy-revisited-the",
      "source": "substack.com",
      "published": "2026-07-11T07:34:36+00:00",
      "tickers": [
        "JPM"
      ]
    },
    {
      "title": "Morgan Stanley Emerging Markets Debt Fund (NYSE:MSD) Shares Down 0.2% - What's Next?",
      "url": "https://www.marketbeat.com/instant-alerts/morgan-stanley-emerging-markets-debt-fund-nysemsd-shares-down-02-whats-next-2026-07-10/",
      "source": "marketbeat.com",
      "published": "2026-07-11T04:20:28+00:00",
      "tickers": [
        "MS"
      ]
    },
    {
      "title": "Red Sox beat Mets after plane problems strand them in Chicago and lead to late arrival",
      "url": "https://wtop.com/sports/2026/07/red-sox-arrive-2-hours-before-scheduled-game-vs-mets-after-team-plane-problems-in-chicago/",
      "source": "wtop.com",
      "published": "2026-07-11T04:10:38+00:00",
      "tickers": [
        "C"
      ]
    },
    {
      "title": "Goldman Sachs Just Made 4 Bold Calls: 2 Sells, 1 Buy, and a $2,159 Price Target On This Popular Stock",
      "url": "https://247wallst.com/investing/2026/07/11/goldman-sachs-just-made-4-bold-calls-2-sells-1-buy-and-a-2159-price-target-on-this-popular-stock/",
      "source": "247wallst.com",
      "published": "2026-07-11T04:02:16+00:00",
      "tickers": [
        "GS"
      ]
    },
    {
      "title": "Mar 31, 2025; Washington, District of Columbia, USA; Miami Heat guard Tyler Herro (14) and center Bam Adebayo (13) react during the third quarter against the Washington Wizards at Capital One Arena. Mandatory Credit: Reggie Hildred-Imagn Images",
      "url": "https://fremonttribune.com/image_0fec7dd0-6073-5f32-ba2e-c065cda5c2d3.html",
      "source": "fremonttribune.com",
      "published": "2026-07-11T01:34:00+00:00",
      "tickers": [
        "C",
        "COF"
      ]
    },
    {
      "title": "A Look at Morgan Stanley (MS) After 0.1% Gain -- GF Value $151.93 vs Price $222.28",
      "url": "https://www.gurufocus.com/news/8954343/a-look-at-morgan-stanley-ms-after-01-gain-gf-value-15193-vs-price-22228",
      "source": "gurufocus.com",
      "published": "2026-07-11T01:31:53+00:00",
      "tickers": [
        "MS"
      ]
    },
    {
      "title": "Morgan Stanley Targets Ethereum and Solana ETF Market Share Amid Intensifying Fee Competition",
      "url": "https://news.bitcoin.com/morgan-stanley-targets-ethereum-and-solana-etf-market-share-amid-intensifying-fee-competition/",
      "source": "bitcoin.com",
      "published": "2026-07-11T01:30:38+00:00",
      "tickers": [
        "MS"
      ]
    },
    {
      "title": "A Look at Bank of America Corp (BAC) After 0.7% Gain -- GF Value $49.95 vs Price $59.67",
      "url": "https://www.gurufocus.com/news/8954337/a-look-at-bank-of-america-corp-bac-after-07-gain-gf-value-4995-vs-price-5967",
      "source": "gurufocus.com",
      "published": "2026-07-11T01:25:53+00:00",
      "tickers": [
        "BAC",
        "C"
      ]
    },
    {
      "title": "Is JPMorgan Chase & Co (JPM) Overvalued After 0.3% Rally? GF Value Says Overvalued",
      "url": "https://www.gurufocus.com/news/8954328/is-jpmorgan-chase-co-jpm-overvalued-after-03-rally-gf-value-says-overvalued",
      "source": "gurufocus.com",
      "published": "2026-07-11T01:16:50+00:00",
      "tickers": [
        "JPM"
      ]
    },
    {
      "title": "Eric Costello & Who Owns Slack in 2026",
      "url": "https://fourweekmba.com/who-owns-slack/?utm_source=rss&utm_medium=rss&utm_campaign=who-owns-slack",
      "source": "fourweekmba.com",
      "published": "2026-07-11T01:03:30+00:00",
      "tickers": [
        "STT"
      ]
    }
  ]
}